urtext/__init__.py
urtext/action.py
urtext/buffer.py
urtext/call.py
urtext/exec.py
urtext/file.py
urtext/frame.py
urtext/link.py
urtext/metadata.py
urtext/metadata_entry.py
urtext/metadata_value.py
urtext/node.py
urtext/project.py
urtext/project_list.py
urtext/syntax.py
urtext/target.py
urtext/timestamp.py
urtext/url.py
urtext/utils.py
urtext/base_project/All Actions Scratch Buffer.urtext
urtext/base_project/All Actions.urtext
urtext/base_project/All Projects Node Browser.urtext
urtext/base_project/Anchor.urtext
urtext/base_project/AsyncOff.urtext
urtext/base_project/Browse Backlinks.urtext
urtext/base_project/Browse Forward Links.urtext
urtext/base_project/Browse Metadata.urtext
urtext/base_project/Collect.urtext
urtext/base_project/Copy Link To Here With Project.urtext
urtext/base_project/Copy Link To Here.urtext
urtext/base_project/Create Starter Project.urtext
urtext/base_project/Delete This Buffer.urtext
urtext/base_project/Export.urtext
urtext/base_project/File Link.urtext
urtext/base_project/File Outline Dropdown.urtext
urtext/base_project/Files.urtext
urtext/base_project/Format.urtext
urtext/base_project/Go To Frame.urtext
urtext/base_project/Home.urtext
urtext/base_project/Include and Exclude.urtext
urtext/base_project/Info.urtext
urtext/base_project/Insert Timestamp.urtext
urtext/base_project/Interlinks.urtext
urtext/base_project/Keybindings to JSON.urtext
urtext/base_project/Limit.urtext
urtext/base_project/Link Preview.urtext
urtext/base_project/Link to New Node.urtext
urtext/base_project/Link to Node.urtext
urtext/base_project/Lint.urtext
urtext/base_project/List Projects.urtext
urtext/base_project/Log.urtext
urtext/base_project/Max Length.urtext
urtext/base_project/Move File To Other Project.urtext
urtext/base_project/Navigation.urtext
urtext/base_project/New File Node.urtext
urtext/base_project/Node Browser.urtext
urtext/base_project/Open Home.urtext
urtext/base_project/Open Link.urtext
urtext/base_project/Patterns.urtext
urtext-0.1.8.dist-info/METADATA
urtext-0.1.8.dist-info/WHEEL
urtext-0.1.8.dist-info/top_level.txt
urtext-0.1.8.dist-info/RECORD
