Metadata-Version: 2.4
Name: urtext
Version: 0.1.8
Summary: Urtext /ˈʊrtekst/ is a markup language and framework for programmable notebooks in text files on top of the Python language.
Requires-Dist: anytree
Requires-Dist: python-dateutil
Requires-Dist: six
